steve_yajl-2.1.3.dev0.dist-info/DESCRIPTION.rst
steve_yajl-2.1.3.dev0.dist-info/METADATA
steve_yajl-2.1.3.dev0.dist-info/RECORD
steve_yajl-2.1.3.dev0.dist-info/WHEEL
steve_yajl-2.1.3.dev0.dist-info/entry_points.txt
steve_yajl-2.1.3.dev0.dist-info/metadata.json
steve_yajl-2.1.3.dev0.dist-info/top_level.txt
steve_yajl-2.1.3.dev0.dist-info/zip-safe
yajl/__init__.py
yajl/libyajl.so.2.1.0
yajl/yajl_common.py
yajl/yajl_gen.py
yajl/yajl_parse.py
