Metadata-Version: 2.0
Name: steve-yajl
Version: 2.1.3.dev0
Summary: Pure Python Yajl Wrapper
Home-page: http://pykler.github.com/yajl-py/
Author: Hatem Nassrat
Author-email: hnassrat@gmail.com
License: PSF
Keywords: yajl json parsing
Platform: UNKNOWN
Requires-Dist: six
